shape_detection/__init__.py
shape_detection/shape.py
shape_detection/square.py
shape_detection/triangle.py
test/__init__.py
test/test_shape.py
test/test_square.py
test/test_triangle.py
shape_detection_jdla-0.0.2.dist-info/LICENSE
shape_detection_jdla-0.0.2.dist-info/METADATA
shape_detection_jdla-0.0.2.dist-info/WHEEL
shape_detection_jdla-0.0.2.dist-info/top_level.txt
shape_detection_jdla-0.0.2.dist-info/RECORD
