Metadata-Version: 2.1
Name: shape-detection-jdla
Version: 0.0.2
Summary: Shape detection using OpenCV
Home-page: https://github.com/JosueDLA/ShapeDetection
Author: Josué de León
Author-email: josuedlavs@gmail.com
License: MIT
Platform: UNKNOWN
Classifier: Programming Language :: Python :: 3
Classifier: License :: OSI Approved :: MIT License
Classifier: Operating System :: OS Independent
Requires-Python: >=3.10
License-File: LICENSE
Requires-Dist: numpy (==1.21.4)
Requires-Dist: opencv-python (==4.5.4.60)
